hanhchinhvn/__init__.py
hanhchinhvn/models.py
hanhchinhvn/data/quan_huyen.json
hanhchinhvn/data/tinh_tp.json
hanhchinhvn/data/tree.json
hanhchinhvn/data/xa_phuong.json
hanhchinhvn/data/quan_huyen/01.json
hanhchinhvn/data/quan_huyen/02.json
hanhchinhvn/data/quan_huyen/04.json
hanhchinhvn/data/quan_huyen/06.json
hanhchinhvn/data/quan_huyen/08.json
hanhchinhvn/data/quan_huyen/10.json
hanhchinhvn/data/quan_huyen/11.json
hanhchinhvn/data/quan_huyen/12.json
hanhchinhvn/data/quan_huyen/14.json
hanhchinhvn/data/quan_huyen/15.json
hanhchinhvn/data/quan_huyen/17.json
hanhchinhvn/data/quan_huyen/19.json
hanhchinhvn/data/quan_huyen/20.json
hanhchinhvn/data/quan_huyen/22.json
hanhchinhvn/data/quan_huyen/24.json
hanhchinhvn/data/quan_huyen/25.json
hanhchinhvn/data/quan_huyen/26.json
hanhchinhvn/data/quan_huyen/27.json
hanhchinhvn/data/quan_huyen/30.json
hanhchinhvn/data/quan_huyen/31.json
hanhchinhvn/data/quan_huyen/33.json
hanhchinhvn/data/quan_huyen/34.json
hanhchinhvn/data/quan_huyen/35.json
hanhchinhvn/data/quan_huyen/36.json
hanhchinhvn/data/quan_huyen/37.json
hanhchinhvn/data/quan_huyen/38.json
hanhchinhvn/data/quan_huyen/40.json
hanhchinhvn/data/quan_huyen/42.json
hanhchinhvn/data/quan_huyen/44.json
hanhchinhvn/data/quan_huyen/45.json
hanhchinhvn/data/quan_huyen/46.json
hanhchinhvn/data/quan_huyen/48.json
hanhchinhvn/data/quan_huyen/49.json
hanhchinhvn/data/quan_huyen/51.json
hanhchinhvn/data/quan_huyen/52.json
hanhchinhvn/data/quan_huyen/54.json
hanhchinhvn/data/quan_huyen/56.json
hanhchinhvn/data/quan_huyen/58.json
hanhchinhvn/data/quan_huyen/60.json
hanhchinhvn/data/quan_huyen/62.json
hanhchinhvn/data/quan_huyen/64.json
hanhchinhvn/data/quan_huyen/66.json
hanhchinhvn/data/quan_huyen/67.json
hanhchinhvn/data/quan_huyen/68.json
hanhchinhvn/data/quan_huyen/70.json
hanhchinhvn/data/quan_huyen/72.json
hanhchinhvn/data/quan_huyen/74.json
hanhchinhvn/data/quan_huyen/75.json
hanhchinhvn/data/quan_huyen/77.json
hanhchinhvn/data/quan_huyen/79.json
hanhchinhvn-0.0.3.dist-info/METADATA
hanhchinhvn-0.0.3.dist-info/WHEEL
hanhchinhvn-0.0.3.dist-info/licenses/LICENSE
hanhchinhvn-0.0.3.dist-info/RECORD
