Metadata-Version: 2.4
Name: hanhchinhvn
Version: 0.0.3
Summary: Vietnam Administrative Divisions (Provinces, Districts, Wards) for Python
Project-URL: Homepage, https://github.com/kumaruseru/hanhchinhvn.git
Author-email: nghia <nghiaht281003@gmail.com>
License: MIT License
License-File: LICENSE
Requires-Python: >=3.8
Requires-Dist: pydantic>=2.0.0
Requires-Dist: text-unidecode>=1.3
